LICENSE
MANIFEST.in
Makefile
README.mkd
setup.cfg
setup.py
tests.py
Flask_ZODB.egg-info/PKG-INFO
Flask_ZODB.egg-info/SOURCES.txt
Flask_ZODB.egg-info/dependency_links.txt
Flask_ZODB.egg-info/namespace_packages.txt
Flask_ZODB.egg-info/not-zip-safe
Flask_ZODB.egg-info/requires.txt
Flask_ZODB.egg-info/top_level.txt
docs/index.rst
examples/flaskr/README
examples/flaskr/flaskr.py
examples/flaskr/flaskr_tests.py
examples/flaskr/static/style.css
examples/flaskr/templates/layout.html
examples/flaskr/templates/login.html
examples/flaskr/templates/show_entries.html
flaskext/__init__.py
flaskext/zodb.py