Metadata-Version: 1.1
Name: Flask-ZODB
Version: 0.1
Summary: Use the ZODB with Flask
Home-page: https://github.com/dag/flask-zodb
Author: Dag Odenhall
Author-email: dag.odenhall@gmail.com
License: BSD
Keywords: flask,zodb,persistence,database
Platform: UNKNOWN
Classifier: Development Status :: 3 - Alpha
Classifier: Environment :: Web Environment
Classifier: Framework :: ZODB
Classifier: Intended Audience :: Developers
Classifier: License :: OSI Approved :: BSD License
Classifier: Operating System :: OS Independent
Classifier: Programming Language :: Python :: 2.5
Classifier: Programming Language :: Python :: 2.6
Classifier: Programming Language :: Python :: 2.7
Classifier: Topic :: Database
Classifier: Topic :: Internet :: WWW/HTTP :: Dynamic Content
Classifier: Topic :: Software Development :: Libraries :: Python Modules
Requires: flask (>=0.7)
Requires: ZODB
Requires: zodburi
